{
    "patches": [
        {
            "label": "2025-10-07_20-00-00",
            "content": "@@ -38,20 +38,16 @@\n our: int\n- = 0\n , minute\n@@ -51,20 +51,16 @@\n ute: int\n- = 0\n , second\n@@ -65,20 +65,16 @@\n nds: int\n- = 0\n ):%0A     \n@@ -97,76 +97,8 @@\n   = \n-0;%0A        self.__minute  = 0;%0A        self.__seconds = 0;%0A%0A        \n self\n@@ -112,32 +112,49 @@\n r(hour);%0A       \n+ self.__minute  =\n  self.setMinute(\n@@ -165,24 +165,41 @@\n te);%0A       \n+ self.__seconds =\n  self.setSec\n@@ -252,26 +252,26 @@\n         \n-hour    = \n+return f%22%7B\n self.get\n@@ -280,137 +280,67 @@\n ur()\n-;%0A        minute  = self.getMinute();%0A        seconds = self.getSeconds();%0A        return f%22%7Bhour:02%7D:%7Bminute:02%7D:%7Bseconds:02%7D%22;%0A\n+:.2d%7D:%7Bself.getMinute():.2d%7D:%7Bself.getSeconds():.2d%7D%22;%0A    \n %0A   \n@@ -377,35 +377,35 @@\n etHour(self) -%3E \n-int\n+str\n :%0A        return\n@@ -438,35 +438,35 @@\n Minute(self) -%3E \n-int\n+str\n :%0A        return\n@@ -510,19 +510,19 @@\n elf) -%3E \n-int\n+str\n :%0A      \n@@ -590,37 +590,32 @@\n Hour(self, value\n-: int\n ):%0A        if va\n@@ -763,21 +763,16 @@\n f, value\n-: int\n ):%0A     \n@@ -937,12 +937,8 @@\n alue\n-:int\n ):%0A \n@@ -1053,23 +1053,22 @@\n  self.__\n-seconds\n+minute\n  = value\n@@ -1131,48 +1131,8 @@\n f):%0A\n-        if self.getSeconds() != 59:%0A    \n     \n@@ -1152,25 +1152,25 @@\n econds(self.\n-g\n+s\n etSeconds() \n@@ -1166,33 +1166,23 @@\n tSeconds\n-()\n  + 1);%0A\n-        \n %0A       \n@@ -1186,32 +1186,17 @@\n     \n-else:%0A           \n+if\n  self.\n-s\n+g\n etSe\n@@ -1201,21 +1201,24 @@\n Seconds(\n-0);%0A \n+) %3E 59:%0A\n         \n@@ -1224,39 +1224,29 @@\n     \n-if\n  self.\n-getMinute() != 59:%0A    \n+setSeconds(0);%0A\n     \n@@ -1295,61 +1295,26 @@\n 1);%0A\n-            %0A            else:%0A               \n+%0A        if\n  self.\n-s\n+g\n etMi\n@@ -1310,38 +1310,40 @@\n  self.getMinute(\n-0);%0A  \n+) %3E 59:%0A\n               if\n@@ -1342,43 +1342,27 @@\n     \n-  if \n self.\n-getHour() != 23:%0A        \n+setMinute(0);%0A\n     \n@@ -1407,38 +1407,41 @@\n 1);%0A\n-                else:%0A        \n+%0A        if self.getHour() %3E 59:%0A\n     \n@@ -1473,32 +1473,24 @@\n             \n-        \n self.setMinu\n@@ -1504,32 +1504,24 @@\n             \n-        \n self.setSeco\n@@ -1527,17 +1527,16 @@\n onds(0);\n- \n %0A%0A      \n@@ -1550,711 +1550,49 @@\n n;%0A%0A\n-def main():%0A    watch = Watch();%0A%0A    while True:%0A        line = input();%0A        args = line.split(%22 %22);%0A        print(f%22$%7Bline%7D%22);%0A        %0A        match args%5B0%5D:%0A            case %22show%22:%0A                print(watch);%0A            %0A            case %22init%22:%0A                watch = Watch(int(args%5B1%5D), int(args%5B2%5D), int(args%5B3%5D));%0A            %0A            case %22set%22:%0A                watch.setHour(int(args%5B1%5D));%0A                watch.setMinute(int(args%5B2%5D));%0A                watch.setSeconds(int(args%5B3%5D));%0A%0A            case %22next%22:%0A                watch.nextScond();%0A%0A            case %22end%22:%0A                break;%0A            %0A            case _:%0A                print(%22fail: comando invalido%22);%0A%0Amain(\n+relogio = Watch(16, 59, 30);%0A%0Aprint(relogio\n );\n",
            "lines": "66"
        },
        {
            "label": "2025-10-08_09-48-48",
            "content": "class Watch:\n    def __init__(self, hour: int = 0, minute: int = 0, seconds: int = 0):\n        self.__hour    = 0;\n        self.__minute  = 0;\n        self.__seconds = 0;\n\n        self.setHour(hour);\n        self.setMinute(minute);\n        self.setSeconds(seconds);\n\n    def __str__(self) -> str:\n        hour    = self.getHour();\n        minute  = self.getMinute();\n        seconds = self.getSeconds();\n        return f\"{hour:02}:{minute:02}:{seconds:02}\";\n\n    # M\u00e9todos de busca\n\n    def getHour(self) -> int:\n        return self.__hour;\n\n    def getMinute(self) -> int:\n        return self.__minute;\n\n    def getSeconds(self) -> int:\n        return self.__seconds;\n\n    # M\u00e9todos mutantes\n\n    def setHour(self, value: int):\n        if value < 0 or value > 23:\n            print(\"fail: hora invalida\");\n            return;\n\n        self.__hour = value;\n    \n    def setMinute(self, value: int):\n        if value < 0 or value > 59:\n            print(\"fail: minuto invalido\");\n            return;\n\n        self.__minute = value;\n    \n    def setSeconds(self, value:int):\n        if value < 0 or value > 59:\n            print(\"fail: segundo invalido\");\n            return;\n\n        self.__seconds = value;\n\n    # M\u00e9todo incrementar tempo\n\n    def nextScond(self):\n        if self.getSeconds() != 59:\n            self.setSeconds(self.getSeconds() + 1);\n        \n        else:\n            self.setSeconds(0);\n            if self.getMinute() != 59:\n                self.setMinute(self.getMinute() + 1);\n            \n            else:\n                self.setMinute(0);\n                if self.getHour() != 23:\n                    self.setHour(self.getHour() + 1);\n                else:\n                    self.setHour(0);\n                    self.setMinute(0);\n                    self.setSeconds(0); \n\n        return;\n\ndef main():\n    watch = Watch();\n\n    while True:\n        line = input();\n        args = line.split(\" \");\n        print(f\"${line}\");\n        \n        match args[0]:\n            case \"show\":\n                print(watch);\n            \n            case \"init\":\n                watch = Watch(int(args[1]), int(args[2]), int(args[3]));\n            \n            case \"set\":\n                watch.setHour(int(args[1]));\n                watch.setMinute(int(args[2]));\n                watch.setSeconds(int(args[3]));\n\n            case \"next\":\n                watch.nextScond();\n\n            case \"end\":\n                break;\n            \n            case _:\n                print(\"fail: comando invalido\");\n\nmain();",
            "lines": "102"
        }
    ]
}